tauspeech/__init__.py
tauspeech/_analytics.py
tauspeech/_cdo.py
tauspeech/_config.py
tauspeech/_parameters.py
tauspeech/_stam.py
tauspeech/_trajectories.py
tauspeech/_trajectory.py
tauspeech/hdf5tools.py
tauspeech/optims.py
tauspeech/segmentation.py
tauspeech/smoothing.py
tauspeech/tautools.py
tauspeech/utils.py
tauspeech/fine_fitting/__init__.py
tauspeech/fine_fitting/_fit.py
tauspeech/fine_fitting/_optimization.py
tauspeech/fine_fitting/_tau.py
tauspeech-0.1.2.dist-info/licenses/LICENSE.txt
tauspeech-0.1.2.dist-info/METADATA
tauspeech-0.1.2.dist-info/WHEEL
tauspeech-0.1.2.dist-info/top_level.txt
tauspeech-0.1.2.dist-info/RECORD
