Metadata-Version: 2.4
Name: tauspeech
Version: 0.1.2
Summary: Tau analysis of speech articulatory movements
Home-page: https://git.ecdf.ed.ac.uk/belie/tauspeech
Author: Benjamin Elie
Author-email: benjamin.elie@ed.ac.uk
License: Creative Commons Attribution 4.0 International License
License-File: LICENSE.txt
Requires-Dist: numpy
Requires-Dist: scipy
Requires-Dist: pytest
Requires-Dist: h5py
Requires-Dist: joblib
Requires-Dist: tqdm
Dynamic: author
Dynamic: author-email
Dynamic: home-page
Dynamic: license
Dynamic: license-file
Dynamic: requires-dist
Dynamic: summary
